src/__init__.py
src/rec_system/__init__.py
src/rec_system/utils.py
src/rec_system/data/__init__.py
src/rec_system/data/recipes.py
src/rec_system/data/survey.py
src/rec_system/data/users.py
src/rec_system/engine/__init__.py
src/rec_system/engine/recommender.py
tests/__init__.py
tests/integration/__init__.py
tests/integration/Data/__init__.py
tests/integration/Data/test_recipes.py
tests/integration/Data/test_survey.py
tests/integration/engine/__init__.py
tests/integration/engine/test_recommender.py
tests/unit/__init__.py
tests/unit/test_utils.py
tests/unit/data/__init__.py
tests/unit/data/test_recipes.py
tests/unit/data/test_survey.py
tests/unit/data/test_users.py
tests/unit/engine/__init__.py
rec_system_trb-0.0.6.dist-info/METADATA
rec_system_trb-0.0.6.dist-info/WHEEL
rec_system_trb-0.0.6.dist-info/top_level.txt
rec_system_trb-0.0.6.dist-info/RECORD
