Metadata-Version: 2.1
Name: rec-system-trb
Version: 0.0.6
Summary: package for recommending dishes in out taste profile, part of engeneering thesis, link to repo https://github.com/Maciekkucharski/AI_DIET_GENERATOR
Author: Trb
Author-email: <m.kucha@wp.pl>
Keywords: python
Classifier: Development Status :: 1 - Planning
Classifier: Intended Audience :: Developers
Classifier: Programming Language :: Python :: 3
Classifier: Operating System :: Unix
Classifier: Operating System :: MacOS :: MacOS X
Classifier: Operating System :: Microsoft :: Windows
